LICENSE
MANIFEST.in
README.rst
setup.cfg
setup.py
RSTLib/__init__.py
RSTLib/main.py
RSTLib.egg-info/PKG-INFO
RSTLib.egg-info/SOURCES.txt
RSTLib.egg-info/dependency_links.txt
RSTLib.egg-info/requires.txt
RSTLib.egg-info/top_level.txt